{
  "accounts": [
    {
      "id": "1",
      "username": "admin",
      "password": "admin",
      "name": "Admin",
      "image": ""
    },
    {
      "name": "thang123",
      "image": "https://cdn.prod.website-files.com/62d84e447b4f9e7263d31e94/6399a4d27711a5ad2c9bf5cd_ben-sweet-2LowviVHZ-E-unsplash-1.jpeg",
      "username": "123",
      "password": "123",
      "id": "01ea"
    },
    {
      "id": "338d",
      "password": "123",
      "username": "ta@gg.gg",
      "name": "thang",
      "image": ""
    },
    {
      "id": "6619",
      "username": "hhh@hh.hh",
      "password": "123",
      "image": "",
      "name": "default"
    },
    {
      "id": "78a7",
      "image": "",
      "name": "default",
      "username": "tt@gmail.com",
      "password": "321"
    },
    {
      "password": "123",
      "username": "thanghoang@gmail.com",
      "name": "thang",
      "image": "https://avatars.githubusercontent.com/u/126375932?v=4",
      "id": "30e8"
    },
    {
      "id": "232e",
      "image": "",
      "name": "default",
      "username": "ta@gg.ggg",
      "password": "123"
    }
  ],
  "task": [
    {
      "id": "121",
      "idAccount": "338d",
      "isGroup": false,
      "title": "go to market",
      "description": "Buy some thing",
      "important": true,
      "date": "12-09-2024",
      "time": "08:59"
    },
    {
      "id": "a84b",
      "idAccount": "338d",
      "description": "Clean my house",
      "date": "12-09-2024",
      "isGroup": false,
      "title": "clean house",
      "important": false,
      "time": "07:59"
    },
    {
      "idAccount": "338",
      "id": "a84b1",
      "description": "Clean my house",
      "date": "12-09-2024",
      "isGroup": false,
      "title": "clean house",
      "important": false,
      "time": "07:59"
    },
    {
      "id": "71af",
      "title": "111",
      "isGroup": false,
      "description": "111",
      "date": "10-09-2024",
      "time": "14:02",
      "important": false,
      "idAccount": "338d"
    }
  ]
}